[
  {
    "name": "master",
    "author": "root",
    "committer": "root",
    "first_commit_str": "2019-04-22 02:59:20",
    "last_commit_str": "2019-04-22 02:59:20",
    "first_commit_date": 1555901960,
    "last_commit_date": 1555901960
  },
  {
    "name": "origin/HEAD",
    "author": "root",
    "committer": "root",
    "first_commit_str": "2019-04-22 02:59:20",
    "last_commit_str": "2019-04-22 02:59:20",
    "first_commit_date": 1555901960,
    "last_commit_date": 1555901960
  },
  {
    "name": "origin/master",
    "author": "root",
    "committer": "root",
    "first_commit_str": "2019-04-22 02:59:20",
    "last_commit_str": "2019-04-22 02:59:20",
    "first_commit_date": 1555901960,
    "last_commit_date": 1555901960
  }
]